{
  "timestamp": "2026-04-14T14:12:23.334618",
  "signal": {
    "signal_id": "ethusd_gate3_1776190343_6450",
    "arb_type": "cross_venue",
    "symbol_a": "ETH-USD",
    "symbol_b": "ETH-USD",
    "venue_a": "coinbase",
    "venue_b": "coinbase",
    "spread_pct": 0.0581,
    "expected_return_pct": 0.0494,
    "confidence": 0.95,
    "timestamp": "2026-04-14T14:12:23.334395",
    "metadata": {
      "gate": "3",
      "market": "ETH-USD",
      "microscopic": true,
      "multi_market": true,
      "test_signal": true,
      "estimated_price": 3025.0932331504455
    }
  },
  "opportunity": {
    "signal": {
      "signal_id": "ethusd_gate3_1776190343_6450",
      "arb_type": "cross_venue",
      "symbol_a": "ETH-USD",
      "symbol_b": "ETH-USD",
      "venue_a": "coinbase",
      "venue_b": "coinbase",
      "spread_pct": 0.0581,
      "expected_return_pct": 0.0494,
      "confidence": 0.95,
      "timestamp": "2026-04-14T14:12:23.334395",
      "metadata": {
        "gate": "3",
        "market": "ETH-USD",
        "microscopic": true,
        "multi_market": true,
        "test_signal": true,
        "estimated_price": 3025.0932331504455
      }
    },
    "decision": "execute",
    "decision_reason": "Approved: ETH-USD risk score 0.723, spread 0.0581%, confidence 0.95",
    "position_size_usd": 0.1,
    "expected_pnl_usd": 4.94e-05,
    "risk_score": 0.7226437037071857,
    "metadata": {
      "approved": true,
      "symbol": "ETH-USD",
      "estimated_slippage_bps": 3.2123125294680905,
      "size_tier": "determined_by_risk",
      "multi_market": true
    }
  },
  "execution_result": {
    "trade_id": "trade_1776190343_6047",
    "timestamp": "2026-04-14T14:12:23.334580",
    "symbol": "ETH-USD",
    "side": "buy",
    "quantity": 3.052240940558308e-05,
    "price": 3025.0932331504455,
    "notional_usd": 0.09233313415227688,
    "fees_usd": 9.233313415227689e-05,
    "slippage_pct": 0.003264331294354913,
    "pnl_usd": -4.6720565881052113e-05,
    "status": "filled",
    "metadata": {
      "gate": "3",
      "order_type": "limit",
      "time_in_force": "GTC",
      "fill_percentage": 92.33313415227687,
      "price_improvement_pct": 0.009906761936218792,
      "limit_order": true,
      "partial_fill": true,
      "multi_market": true,
      "symbol": "ETH-USD"
    }
  },
  "session_id": "gate3_1776190276",
  "gate": "3"
}