[
  {
    "timestamp": "2026-04-12T02:00:44.461045",
    "agent_id": "compliance_agent_001",
    "action": "track_regulation",
    "details": {
      "regulation_id": "reg_20260412_020044",
      "name": "General Data Protection Regulation (GDPR)",
      "type": "data_privacy",
      "jurisdiction": "EU",
      "issuing_agency": "European Commission"
    },
    "compliance_standard": "ISO 19600:2014 (Compliance Management)",
    "security_level": "confidential"
  },
  {
    "timestamp": "2026-04-12T02:00:44.461347",
    "agent_id": "compliance_agent_001",
    "action": "assess_compliance",
    "details": {
      "requirement_id": "req_20260412_020044",
      "regulation_id": "reg_20260412_020044",
      "risk_level": "high",
      "status": "in_review"
    },
    "compliance_standard": "ISO 19600:2014 (Compliance Management)",
    "security_level": "confidential"
  },
  {
    "timestamp": "2026-04-12T02:00:44.461677",
    "agent_id": "compliance_agent_001",
    "action": "create_policy",
    "details": {
      "policy_id": "policy_20260412_020044",
      "title": "Data Protection and Privacy Policy",
      "version": "1.0",
      "regulation_count": 1,
      "status": "draft"
    },
    "compliance_standard": "ISO 19600:2014 (Compliance Management)",
    "security_level": "confidential"
  },
  {
    "timestamp": "2026-04-12T02:00:44.462027",
    "agent_id": "compliance_agent_001",
    "action": "monitor_deadlines",
    "details": {
      "days_ahead": 30,
      "deadlines_found": 0,
      "high_priority": 0
    },
    "compliance_standard": "ISO 19600:2014 (Compliance Management)",
    "security_level": "confidential"
  },
  {
    "timestamp": "2026-04-12T02:04:04.657695",
    "agent_id": "compliance_agent_001",
    "action": "track_regulation",
    "details": {
      "regulation_id": "reg_20260412_020404",
      "name": "General Data Protection Regulation (GDPR)",
      "type": "data_privacy",
      "jurisdiction": "EU",
      "issuing_agency": "European Commission"
    },
    "compliance_standard": "ISO 19600:2014 (Compliance Management)",
    "security_level": "confidential"
  },
  {
    "timestamp": "2026-04-12T02:04:04.658176",
    "agent_id": "compliance_agent_001",
    "action": "assess_compliance",
    "details": {
      "requirement_id": "req_20260412_020404",
      "regulation_id": "reg_20260412_020404",
      "risk_level": "high",
      "status": "in_review"
    },
    "compliance_standard": "ISO 19600:2014 (Compliance Management)",
    "security_level": "confidential"
  },
  {
    "timestamp": "2026-04-12T02:04:04.658863",
    "agent_id": "compliance_agent_001",
    "action": "create_policy",
    "details": {
      "policy_id": "policy_20260412_020404",
      "title": "Data Protection and Privacy Policy",
      "version": "1.0",
      "regulation_count": 1,
      "status": "draft"
    },
    "compliance_standard": "ISO 19600:2014 (Compliance Management)",
    "security_level": "confidential"
  },
  {
    "timestamp": "2026-04-12T02:04:04.659129",
    "agent_id": "compliance_agent_001",
    "action": "monitor_deadlines",
    "details": {
      "days_ahead": 30,
      "deadlines_found": 0,
      "high_priority": 0
    },
    "compliance_standard": "ISO 19600:2014 (Compliance Management)",
    "security_level": "confidential"
  }
]